{
    "id": "postclaw",
    "name": "PostClaw",
    "version": "1.0.0",
    "kind": "memory",
    "description": "PostgreSQL-backed RAG, memory, and persona management",
    "configSchema": {
        "type": "object",
        "additionalProperties": false,
        "properties": {
            "dbUrl": {
                "type": "string",
                "description": "PostgreSQL connection string (with pgvector extension enabled)"
            },
            "adminDbUrl": {
                "type": "string",
                "description": "PostgreSQL superuser connection string (used by setup command only)"
            },
            "sleepIntervalHours": {
                "type": "number",
                "description": "Hours between background sleep cycles (default: 6, set to 0 to disable)"
            }
        }
    },
    "uiHints": {
        "dbUrl": {
            "label": "Database URL",
            "placeholder": "postgres://user:pass@localhost:5432/memorydb",
            "sensitive": true
        },
        "adminDbUrl": {
            "label": "Admin Database URL",
            "placeholder": "postgres://postgres:pass@localhost:5432/postgres",
            "sensitive": true
        }
    }
}